hindsight_litellm/__init__.py
hindsight_litellm/callbacks.py
hindsight_litellm/config.py
hindsight_litellm/wrappers.py
hindsight_litellm-0.4.7.dist-info/METADATA
hindsight_litellm-0.4.7.dist-info/WHEEL
hindsight_litellm-0.4.7.dist-info/RECORD
