Metadata-Version: 2.4
Name: hindsight-litellm
Version: 0.4.7
Summary: Universal LLM memory integration via LiteLLM - works with 100+ providers
Project-URL: Homepage, https://github.com/vectorize-io/hindsight
Project-URL: Documentation, https://github.com/vectorize-io/hindsight/tree/main/hindsight-integrations/litellm
Project-URL: Repository, https://github.com/vectorize-io/hindsight
Author-email: Vectorize <support@vectorize.io>
License: MIT
Keywords: agents,ai,anthropic,groq,hindsight,langchain,litellm,llm,memory,openai
Classifier: Development Status :: 4 - Beta
Classifier: Intended Audience :: Developers
Classifier: License :: OSI Approved :: MIT License
Classifier: Programming Language :: Python :: 3
Classifier: Programming Language :: Python :: 3.10
Classifier: Programming Language :: Python :: 3.11
Classifier: Programming Language :: Python :: 3.12
Classifier: Topic :: Scientific/Engineering :: Artificial Intelligence
Requires-Python: >=3.10
Requires-Dist: aiohttp>=3.13.3
Requires-Dist: filelock>=3.20.3
Requires-Dist: litellm>=1.40.0
Requires-Dist: urllib3>=2.6.3
Provides-Extra: dev
Requires-Dist: pytest-asyncio>=0.21.0; extra == 'dev'
Requires-Dist: pytest-mock>=3.10.0; extra == 'dev'
Requires-Dist: pytest>=7.0.0; extra == 'dev'
